apollo_dlc_model_light/__init__.py
apollo_dlc_model_light/config.yaml
apollo_dlc_model_light/dlc-models/iteration-0/apollo_implantNov1-trainset95shuffle1/test/pose_cfg.yaml
apollo_dlc_model_light/dlc-models/iteration-0/apollo_implantNov1-trainset95shuffle1/train/checkpoint
apollo_dlc_model_light/dlc-models/iteration-0/apollo_implantNov1-trainset95shuffle1/train/learning_stats.csv
apollo_dlc_model_light/dlc-models/iteration-0/apollo_implantNov1-trainset95shuffle1/train/log.txt
apollo_dlc_model_light/dlc-models/iteration-0/apollo_implantNov1-trainset95shuffle1/train/pose_cfg.yaml
apollo_dlc_model_light/dlc-models/iteration-0/apollo_implantNov1-trainset95shuffle1/train/snapshot-1030000.data-00000-of-00001
apollo_dlc_model_light/dlc-models/iteration-0/apollo_implantNov1-trainset95shuffle1/train/snapshot-1030000.index
apollo_dlc_model_light/dlc-models/iteration-0/apollo_implantNov1-trainset95shuffle1/train/snapshot-1030000.meta
apollo_dlc_model_light/evaluation-results/iteration-0/CombinedEvaluation-results.csv
apollo_dlc_model_light/evaluation-results/iteration-0/apollo_implantNov1-trainset95shuffle1/DLC_resnet50_apollo_implantNov1shuffle1_1030000-results.csv
apollo_dlc_model_light/evaluation-results/iteration-0/apollo_implantNov1-trainset95shuffle1/DLC_resnet50_apollo_implantNov1shuffle1_1030000-snapshot-1030000.h5
apollo_dlc_model_light/training-datasets/iteration-0/UnaugmentedDataSet_apollo_implantNov1/CollectedData_slenzi.csv
apollo_dlc_model_light/training-datasets/iteration-0/UnaugmentedDataSet_apollo_implantNov1/CollectedData_slenzi.h5
apollo_dlc_model_light/training-datasets/iteration-0/UnaugmentedDataSet_apollo_implantNov1/Documentation_data-apollo_implant_95shuffle1.pickle
apollo_dlc_model_light/training-datasets/iteration-0/UnaugmentedDataSet_apollo_implantNov1/apollo_implant_slenzi95shuffle1.mat
lmtracker/__init__.py
lmtracker/default_params.py
lmtracker/process_DLC_output.py
lmtracker/readme.MD
lmtracker/track_mouse.py
lmtracker/transfer.py
lmtracker-0.1.0.dist-info/LICENSE
lmtracker-0.1.0.dist-info/METADATA
lmtracker-0.1.0.dist-info/WHEEL
lmtracker-0.1.0.dist-info/top_level.txt
lmtracker-0.1.0.dist-info/RECORD
