Metadata-Version: 2.1
Name: lmtracker
Version: 0.1.0
Summary: dlc tracking modules
Author-email: Stephen Lenzi <stephen.lenzi@gmail.com>
License: MIT
Project-URL: Homepage, https://github.com/stephenlenzi/lmtracker
Project-URL: Bug Tracker, https://github.com/stephenlenzi/lmtracker/issues
Project-URL: Documentation, https://stephenlenzi.github.io/lmtracker
Project-URL: Source Code, https://github.com/stephenlenzi/lmtracker
Project-URL: User Support, https://github.com/stephenlenzi/lmtracker/issues
Classifier: Development Status :: 2 - Pre-Alpha
Classifier: Programming Language :: Python
Classifier: Programming Language :: Python :: 3
Classifier: Programming Language :: Python :: 3.9
Classifier: Programming Language :: Python :: 3.10
Classifier: Programming Language :: Python :: 3.11
Classifier: Operating System :: OS Independent
Classifier: License :: OSI Approved :: MIT License
Requires-Python: >=3.9.0
License-File: LICENSE
Requires-Dist: tensorflow==2.10.0
Requires-Dist: deeplabcut==2.3.5
Requires-Dist: numpy
Requires-Dist: matplotlib
Requires-Dist: pims
Requires-Dist: scikit-video
Requires-Dist: scikit-image
Requires-Dist: opencv-python
Requires-Dist: tables
Requires-Dist: fire
Provides-Extra: dev
Requires-Dist: pytest; extra == "dev"
Requires-Dist: pytest-cov; extra == "dev"
Requires-Dist: coverage; extra == "dev"
Requires-Dist: tox; extra == "dev"
Requires-Dist: mypy; extra == "dev"
Requires-Dist: pre-commit; extra == "dev"
Requires-Dist: ruff; extra == "dev"
Requires-Dist: setuptools-scm; extra == "dev"
